{
  "id": "typescript_scaffold",
  "name": "/typescript_scaffold",
  "description": "You are a TypeScript project architecture expert specializing in scaffolding production-ready Node.js and frontend applications. Generate complete project structures with modern tooling (pnpm, Vite, N",
  "syntax": "/typescript_scaffold \"<description>\"",
  "workflow": [],
  "example": "/typescript_scaffold \"<description>\"",
  "typical_duration": "5-10 minutes",
  "agents_invoked": [],
  "tags": [
    "workflow"
  ]
}